[
  {
    "id": 1,
    "title": "Капибарное",
    "place": "Лавка",
    "image": "./images/karbo.png"
  },
  {
    "id": 2,
    "title": "Круассан",
    "place": "ВкусВилл",
    "image": "https://static.insales-cdn.com/r/fHWCzc4AlFA/rs:fit:1200:1200:1/plain/images/products/1/8181/214114293/kruassan-vkusvill-90g.jpg@jpg"
  },
  {
    "id": 3,
    "title": "Супчик куриновый",
    "place": "ВкусВилл",
    "image": "./images/soup.webp"
  },
  {
    "id": 4,
    "title": "Питса (как в прошлый раз)",
    "place": "ДоДо",
    "image": "./images/pizaa.jpg"
  },
  {
    "id": 5,
    "title": "Питса (сам реши)",
    "place": "гденибудь",
    "image": "./images/pizza.jpg"
  },
  {
    "id": 6,
    "title": "Хот Доги",
    "place": "сам сделай суко",
    "image": "./images/hot-dog.png"
  },
  {
    "id": 7,
    "title": "Шава",
    "place": "сам сделай суко",
    "image": "./images/shava.jpg"
  }
]
